{
  "version": 1,
  "terms": [
    {
      "id": 1,
      "cn": "水军",
      "en": "Paid Trolls/Paid Commenters",
      "cat": "通用",
      "def": "受雇发布特定内容影响舆论的群体",
      "ex": "竞品雇用水军刷差评，需要监测应对。"
    },
    {
      "id": 2,
      "cn": "营销号",
      "en": "Marketing Account/Promotional Account",
      "cat": "通用",
      "def": "以流量变现为目的批量生产营销内容的账号",
      "ex": "这篇笔记是营销号写的，全是软广。"
    },
    {
      "id": 3,
      "cn": "种草",
      "en": "Planting Grass",
      "cat": "通用",
      "def": "通过内容推荐激发购买欲望",
      "ex": "这个博主种草能力很强，推荐的产品经常卖断货。"
    },
    {
      "id": 4,
      "cn": "拔草",
      "en": "Pulling Grass",
      "cat": "通用",
      "def": "因负面评价 / 价格高等原因打消购买念头",
      "ex": "本来想买的，看到差评被拔草了。"
    },
    {
      "id": 5,
      "cn": "收割",
      "en": "Monetization（变现）/Conversion（转化）",
      "cat": "通用",
      "def": "将积累的流量 / 粉丝转化为实际销售",
      "ex": "私域流量池建好后开始收割，转化率 15%。"
    },
    {
      "id": 6,
      "cn": "长草",
      "en": "Develop Purchase Desire/Generate Buying Interest",
      "cat": "通用",
      "def": "对某物产生强烈购买欲望的状态",
      "ex": "对这个包长草半年了，终于入手了。"
    },
    {
      "id": 7,
      "cn": "私域流量",
      "en": "Private Traffic",
      "cat": "通用",
      "def": "品牌自主拥有、可免费反复触达的流量",
      "ex": "搭建私域流量池可以降低获客成本。"
    },
    {
      "id": 8,
      "cn": "公域流量",
      "en": "Public Traffic",
      "cat": "通用",
      "def": "平台拥有、需付费或竞争获取的流量",
      "ex": "公域流量越来越贵，必须转向私域。"
    },
    {
      "id": 9,
      "cn": "泛流量",
      "en": "Generic Traffic",
      "cat": "通用",
      "def": "不精准、转化率低的广泛流量",
      "ex": "泛流量再多也不如 1000 个精准用户。"
    },
    {
      "id": 10,
      "cn": "精准流量",
      "en": "Targeted Traffic",
      "cat": "通用",
      "def": "有明确需求、转化率高的目标用户",
      "ex": "通过 SEO 来的都是精准流量。"
    },
    {
      "id": 11,
      "cn": "存量市场",
      "en": "Existing Market",
      "cat": "通用",
      "def": "用户增长见顶，需争夺现有用户的市场",
      "ex": "进入存量竞争时代，复购率是关键。"
    },
    {
      "id": 12,
      "cn": "增量市场",
      "en": "Growth Market",
      "cat": "通用",
      "def": "仍有新用户增长空间的市场",
      "ex": "海外市场是重要的增量市场。"
    },
    {
      "id": 13,
      "cn": "裂变",
      "en": "Viral Growth",
      "cat": "通用",
      "def": "通过用户分享实现指数级增长",
      "ex": "拼多多的拼团是典型裂变玩法。"
    },
    {
      "id": 14,
      "cn": "下沉市场",
      "en": "Lower-Tier Markets",
      "cat": "通用",
      "def": "三线及以下城市、县镇和农村市场",
      "ex": "下沉市场用户增长快，客单价较低。"
    },
    {
      "id": 15,
      "cn": "小镇青年",
      "en": "Small-Town Youth",
      "cat": "通用",
      "def": "来自三四线城市的年轻消费群体",
      "ex": "小镇青年有闲有钱，是消费升级重要力量。"
    },
    {
      "id": 16,
      "cn": "Z 世代",
      "en": "Gen Z",
      "cat": "通用",
      "def": "1995-2009 年出生的人群，数字原生代",
      "ex": "Z 世代更注重品牌价值观和个性化。"
    },
    {
      "id": 17,
      "cn": "她经济",
      "en": "She-Conomy",
      "cat": "通用",
      "def": "女性消费市场的经济现象",
      "ex": "她经济驱动了美妆、母婴、健康品类增长。"
    },
    {
      "id": 18,
      "cn": "国潮",
      "en": "China Chic",
      "cat": "通用",
      "def": "中国本土品牌和文化元素的潮流化",
      "ex": "国潮崛起，李宁、花西子受年轻人追捧。"
    },
    {
      "id": 19,
      "cn": "内卷",
      "en": "Involution",
      "cat": "通用",
      "def": "过度竞争导致收益递减的现象",
      "ex": "流量内卷严重，获客成本逐年攀升。"
    },
    {
      "id": 20,
      "cn": "破圈",
      "en": "Break The Circle",
      "cat": "通用",
      "def": "突破原有受众范围，触达更广泛人群",
      "ex": "这次营销成功破圈，从核心用户扩展到大众。"
    },
    {
      "id": 21,
      "cn": "心智占领",
      "en": "Mindshare Occupation",
      "cat": "通用",
      "def": "在消费者心智中建立品牌认知",
      "ex": "提到可乐就想到可口可乐。"
    },
    {
      "id": 22,
      "cn": "品效合一",
      "en": "Brand & Performance Integration",
      "cat": "通用",
      "def": "品牌建设和效果营销相结合",
      "ex": "品效合一是现代营销的理想状态。"
    },
    {
      "id": 23,
      "cn": "黑稿",
      "en": "Negative PR",
      "cat": "通用",
      "def": "恶意负面内容（可能竞品投放）",
      "ex": "监测到黑稿，需要危机公关应对。"
    },
    {
      "id": 24,
      "cn": "洗稿",
      "en": "Content Plagiarism",
      "cat": "通用",
      "def": "改写他人内容据为己有",
      "ex": "这篇笔记被洗稿了，要维权。"
    },
    {
      "id": 25,
      "cn": "带节奏",
      "en": "Leading The Narrative",
      "cat": "通用",
      "def": "引导舆论方向",
      "ex": "有人在带节奏，需要澄清。"
    },
    {
      "id": 26,
      "cn": "翻车",
      "en": "Marketing Fiasco",
      "cat": "通用",
      "def": "营销活动 / 产品出现负面舆情或严重问题",
      "ex": "这次直播翻车了，主播说错话；这款新机翻车了，发热严重。"
    },
    {
      "id": 27,
      "cn": "塌房",
      "en": "Scandal",
      "cat": "通用",
      "def": "代言人 / KOL 出现负面事件",
      "ex": "代言人塌房，品牌紧急下架物料。"
    },
    {
      "id": 28,
      "cn": "限流",
      "en": "Traffic Restriction",
      "cat": "通用",
      "def": "账号 / 内容被系统降低推荐权重",
      "ex": "这条视频疑似被限流了。"
    },
    {
      "id": 29,
      "cn": "封禁",
      "en": "Ban",
      "cat": "通用",
      "def": "账号因违规被禁止直播 / 发布",
      "ex": "虚假宣传直接封禁 7 天。"
    },
    {
      "id": 30,
      "cn": "违规词",
      "en": "Prohibited Terms",
      "cat": "通用",
      "def": "平台禁止使用的宣传用语",
      "ex": "说最好用会被判违规词限流。"
    },
    {
      "id": 31,
      "cn": "敏感词",
      "en": "Sensitive Terms",
      "cat": "通用",
      "def": "可能触发审核的词汇",
      "ex": "医疗类词汇都是敏感词。"
    },
    {
      "id": 32,
      "cn": "引流",
      "en": "Traffic Guidance",
      "cat": "通用",
      "def": "将用户引导至私域或其他平台",
      "ex": "直接引流微信会被判违规。"
    },
    {
      "id": 33,
      "cn": "导流",
      "en": "Platform Diversion",
      "cat": "通用",
      "def": "引导用户离开当前平台",
      "ex": "评论区导流容易被屏蔽。"
    },
    {
      "id": 34,
      "cn": "ROI",
      "en": "Return On Investment",
      "cat": "通用",
      "def": "投资回报率",
      "ex": "(收入 - 成本)/ 成本 × 100%"
    },
    {
      "id": 35,
      "cn": "ROAS",
      "en": "Return On Ad Spend",
      "cat": "通用",
      "def": "广告支出回报率",
      "ex": "广告收入 / 广告支出"
    },
    {
      "id": 36,
      "cn": "GMV",
      "en": "Gross Merchandise Volume",
      "cat": "通用",
      "def": "商品交易总额",
      "ex": "双 11 期间 GMV 突破 1 亿。"
    },
    {
      "id": 37,
      "cn": "UV",
      "en": "Unique Visitor",
      "cat": "通用",
      "def": "独立访客数",
      "ex": "活动页面 UV 达到 10 万。"
    },
    {
      "id": 38,
      "cn": "PV",
      "en": "Page View",
      "cat": "通用",
      "def": "页面浏览量",
      "ex": "首页 PV 是 UV 的 5 倍。"
    },
    {
      "id": 39,
      "cn": "DAU",
      "en": "Daily Active Users",
      "cat": "通用",
      "def": "日活跃用户数",
      "ex": "APP 的 DAU 突破 100 万。"
    },
    {
      "id": 40,
      "cn": "MAU",
      "en": "Monthly Active Users",
      "cat": "通用",
      "def": "月活跃用户数",
      "ex": "MAU 稳定在 500 万。"
    },
    {
      "id": 41,
      "cn": "CVR",
      "en": "Conversion Rate",
      "cat": "通用",
      "def": "转化率",
      "ex": "转化人数 / 访问人数 × 100%"
    },
    {
      "id": 42,
      "cn": "ATV",
      "en": "Average Transaction Value",
      "cat": "通用",
      "def": "客单价",
      "ex": "销售额 / 订单数"
    },
    {
      "id": 43,
      "cn": "复购率",
      "en": "Repurchase Rate",
      "cat": "通用",
      "def": "再次购买用户占比",
      "ex": "复购人数 / 总用户数 × 100%"
    },
    {
      "id": 44,
      "cn": "留存率",
      "en": "Retention Rate",
      "cat": "通用",
      "def": "用户在特定时间后仍活跃的比例",
      "ex": "次日留存率 40%，7 日留存率 20%。"
    },
    {
      "id": 45,
      "cn": "流失率",
      "en": "Churn Rate",
      "cat": "通用",
      "def": "特定时期内停止使用服务的用户比例",
      "ex": "减少 5% 流失率可以翻倍利润。"
    },
    {
      "id": 46,
      "cn": "A/B 测试",
      "en": "A/B Testing",
      "cat": "通用",
      "def": "同时测试两个版本以确定哪个效果更好",
      "ex": "落地页 A/B 测试，版本 B 转化率高 30%。"
    },
    {
      "id": 47,
      "cn": "落地页",
      "en": "Landing Page",
      "cat": "通用",
      "def": "用户点击广告后到达的第一个页面",
      "ex": "落地页优化是提升转化率的关键。"
    },
    {
      "id": 48,
      "cn": "信息流广告",
      "en": "Feed Ads",
      "cat": "通用",
      "def": "混在内容流中的原生广告",
      "ex": "抖音信息流广告 CTR 比横幅高 3 倍。"
    },
    {
      "id": 49,
      "cn": "搜索广告",
      "en": "Search Ads",
      "cat": "通用",
      "def": "在搜索结果中展示的广告",
      "ex": "百度搜索广告按点击付费。"
    },
    {
      "id": 50,
      "cn": "展示广告",
      "en": "Display Ads",
      "cat": "通用",
      "def": "以图片、视频等形式展示的广告",
      "ex": "展示广告适合提升品牌知名度。"
    },
    {
      "id": 51,
      "cn": "DSP",
      "en": "Demand-Side Platform",
      "cat": "通用",
      "def": "需求方平台，广告主购买广告库存的平台",
      "ex": "通过 DSP 可跨多个交易所竞价。"
    },
    {
      "id": 52,
      "cn": "SSP",
      "en": "Supply-Side Platform",
      "cat": "通用",
      "def": "供给方平台，媒体管理广告库存的平台",
      "ex": "媒体用 SSP 最大化广告位收益。"
    },
    {
      "id": 53,
      "cn": "DMP",
      "en": "Data Management Platform",
      "cat": "通用",
      "def": "数据管理平台，收集管理和激活用户数据",
      "ex": "DMP 帮助建立精准用户画像。"
    },
    {
      "id": 54,
      "cn": "CDP",
      "en": "Customer Data Platform",
      "cat": "通用",
      "def": "客户数据平台，整合多渠道客户数据",
      "ex": "CDP 打通线上线下数据。"
    },
    {
      "id": 55,
      "cn": "第一方数据",
      "en": "First-Party Data",
      "cat": "通用",
      "def": "品牌直接从客户收集的数据",
      "ex": "第一方数据比第三方 cookies 更可靠。"
    },
    {
      "id": 56,
      "cn": "SCRM",
      "en": "Social CRM",
      "cat": "通用",
      "def": "社交化客户关系管理",
      "ex": "企业微信是典型的 SCRM 工具。"
    },
    {
      "id": 57,
      "cn": "养号",
      "en": "Account Nurturing",
      "cat": "通用",
      "def": "新账号通过正常互动建立权重",
      "ex": "养号 3 天再发内容。"
    },
    {
      "id": 58,
      "cn": "权重",
      "en": "Account Weight",
      "cat": "通用",
      "def": "账号在系统中的推荐优先级",
      "ex": "权重高了笔记自然流量就好。"
    },
    {
      "id": 59,
      "cn": "打标签",
      "en": "Tagging",
      "cat": "通用",
      "def": "让系统识别账号内容类型",
      "ex": "连续发垂直内容快速打标签。"
    },
    {
      "id": 60,
      "cn": "人设",
      "en": "Persona",
      "cat": "通用",
      "def": "账号塑造的人物形象",
      "ex": "人设要清晰一致才能吸粉。"
    },
    {
      "id": 61,
      "cn": "垂直领域",
      "en": "Vertical Niche",
      "cat": "通用",
      "def": "专注某一细分内容方向",
      "ex": "越垂直越容易打标签。"
    },
    {
      "id": 62,
      "cn": "真香",
      "en": "Acquired Taste/Grow on Someone",
      "cat": "通用",
      "def": "原本不看好但实际体验后很满意",
      "ex": "发布前被骂惨，用后真香。"
    },
    {
      "id": 63,
      "cn": "KOL",
      "en": "Key Opinion Leader",
      "cat": "直播",
      "def": "关键意见领袖，在特定领域有影响力的网络红人",
      "ex": "找了 5 个美妆 KOL 做新品推广。"
    },
    {
      "id": 64,
      "cn": "KOC",
      "en": "Key Opinion Consumer",
      "cat": "直播",
      "def": "关键意见消费者，普通用户中有影响力的人",
      "ex": "KOC 的真实体验分享比 KOL 更有说服力。"
    },
    {
      "id": 65,
      "cn": "素人",
      "en": "Ordinary User",
      "cat": "直播",
      "def": "普通用户账号（非达人 / KOL）",
      "ex": "找 100 个素人铺量做口碑。"
    },
    {
      "id": 66,
      "cn": "种草号",
      "en": "Seeding Account",
      "cat": "直播",
      "def": "以产品推荐为主的账号",
      "ex": "这个种草号粉丝不多但转化很高。"
    },
    {
      "id": 67,
      "cn": "矩阵号",
      "en": "Matrix Accounts",
      "cat": "直播",
      "def": "同一主体运营的多个账号",
      "ex": "做矩阵号分散风险，覆盖更多人群。"
    },
    {
      "id": 68,
      "cn": "带货",
      "en": "Live Commerce",
      "cat": "直播",
      "def": "通过直播或内容推荐直接促成销售",
      "ex": "这个主播带货能力太强，一场卖了 1000 万。"
    },
    {
      "id": 69,
      "cn": "坑位费",
      "en": "Slotting Fee",
      "cat": "直播",
      "def": "商家为获得直播 / 推荐位支付的固定费用",
      "ex": "头部主播坑位费动辄几十万。"
    },
    {
      "id": 70,
      "cn": "佣金",
      "en": "Commission",
      "cat": "直播",
      "def": "按销售额比例支付给推广者的报酬",
      "ex": "给 KOC 设置 20% 佣金激励推广。"
    },
    {
      "id": 71,
      "cn": "纯佣",
      "en": "Commission Only",
      "cat": "直播",
      "def": "无坑位费，只按销售分成",
      "ex": "中小主播常用纯佣模式合作。"
    },
    {
      "id": 72,
      "cn": "破价",
      "en": "Price Breaking",
      "cat": "直播",
      "def": "直播价格低于日常售价",
      "ex": "破价 5 折是常见直播话术。"
    },
    {
      "id": 73,
      "cn": "机制",
      "en": "Deal Mechanism",
      "cat": "直播",
      "def": "直播间的优惠组合（买赠 / 满减 / 券后价）",
      "ex": "这个机制很好，买一送一还包邮。"
    },
    {
      "id": 74,
      "cn": "过款",
      "en": "Quick Display",
      "cat": "直播",
      "def": "快速展示多个产品（每个 1-2 分钟）",
      "ex": "服装直播常用过款模式。"
    },
    {
      "id": 75,
      "cn": "憋单",
      "en": "Holding Orders",
      "cat": "直播",
      "def": "故意延迟上架 / 放库存，制造紧迫感",
      "ex": "憋单 5 分钟，在线人数翻倍。"
    },
    {
      "id": 76,
      "cn": "放单",
      "en": "Releasing Orders",
      "cat": "直播",
      "def": "正式上架商品开放购买",
      "ex": "准备放单，321 上链接！"
    },
    {
      "id": 77,
      "cn": "逼单",
      "en": "Pushing Sales",
      "cat": "直播",
      "def": "用话术 / 优惠催促用户下单",
      "ex": "最后 3 单，逼单话术用起来。"
    },
    {
      "id": 78,
      "cn": "GPM",
      "en": "Revenue Per Mille",
      "cat": "直播",
      "def": "千次观看成交额",
      "ex": "GPM 做到 500 以上才能持续投流。"
    },
    {
      "id": 79,
      "cn": "CPE",
      "en": "Cost Per Engagement",
      "cat": "直播",
      "def": "单次互动成本",
      "ex": "CPE 控制在 2 块以内算合理。"
    },
    {
      "id": 80,
      "cn": "CES",
      "en": "Content Effectiveness Score",
      "cat": "直播",
      "def": "内容效果评分（小红书内部指标）",
      "ex": "CES 分高才有机会进更大流量池。"
    },
    {
      "id": 81,
      "cn": "UV 价值",
      "en": "UV Value",
      "cat": "直播",
      "def": "每个用户产生的平均价值",
      "ex": "UV 价值 = GMV / 观看人数。"
    },
    {
      "id": 82,
      "cn": "DOU+",
      "en": "DOU+",
      "cat": "抖音",
      "def": "抖音官方内容加热工具，付费提升视频曝光",
      "ex": "这条视频投了 500 块 DOU+，播放量涨了 10 万。"
    },
    {
      "id": 83,
      "cn": "千川",
      "en": "Qianchuan",
      "cat": "抖音",
      "def": "抖音电商广告平台，用于直播带货投放",
      "ex": "千川投放 ROI 做到 1:5 才不亏。"
    },
    {
      "id": 84,
      "cn": "星图",
      "en": "Xingtu",
      "cat": "抖音",
      "def": "抖音官方达人接单平台",
      "ex": "通过星图下单有平台保障。"
    },
    {
      "id": 85,
      "cn": "小黄车",
      "en": "Yellow Cart",
      "cat": "抖音",
      "def": "直播间 / 视频中的购物车图标",
      "ex": "直播间小黄车已上架，3 号链接抓紧拍。"
    },
    {
      "id": 86,
      "cn": "橱窗",
      "en": "Showcase",
      "cat": "抖音",
      "def": "达人主页的商品展示区",
      "ex": "开通橱窗需要 1000 粉丝。"
    },
    {
      "id": 87,
      "cn": "流量层级",
      "en": "Traffic Tier",
      "cat": "抖音",
      "def": "抖音根据账号表现分配的流量池级别",
      "ex": "从一级流量池冲到三级就算小爆了。"
    },
    {
      "id": 88,
      "cn": "自然流",
      "en": "Organic Traffic",
      "cat": "抖音",
      "def": "非付费的系统推荐流量",
      "ex": "自然流占比越高利润越好。"
    },
    {
      "id": 89,
      "cn": "付费流",
      "en": "Paid Traffic",
      "cat": "抖音",
      "def": "通过 DOU+/ 千川购买的流量",
      "ex": "付费流占比超过 70% 很难盈利。"
    },
    {
      "id": 90,
      "cn": "场观",
      "en": "Live Views",
      "cat": "抖音",
      "def": "单场直播累计观看人数",
      "ex": "这场场观 50 万，GMV 100 万。"
    },
    {
      "id": 91,
      "cn": "在线峰值",
      "en": "Peak Concurrent",
      "cat": "抖音",
      "def": "直播间同时在线人数最高值",
      "ex": "在线峰值破万，流量层级提升了。"
    },
    {
      "id": 92,
      "cn": "停留时长",
      "en": "Watch Time",
      "cat": "抖音",
      "def": "用户平均在直播间停留时间",
      "ex": "停留时长做到 1 分钟以上才能留住流量。"
    },
    {
      "id": 93,
      "cn": "转粉率",
      "en": "Follow Rate",
      "cat": "抖音",
      "def": "观看用户转化为粉丝的比例",
      "ex": "转粉率达到 3%-5% 为优秀。"
    },
    {
      "id": 94,
      "cn": "直播切片",
      "en": "Live Clips",
      "cat": "抖音",
      "def": "将直播精彩片段剪辑成短视频二次传播",
      "ex": "直播切片能带来长尾流量。"
    },
    {
      "id": 95,
      "cn": "起号",
      "en": "Account Launch",
      "cat": "抖音",
      "def": "新账号从 0 开始运营到稳定流量",
      "ex": "起号期至少需要 2 周。"
    },
    {
      "id": 96,
      "cn": "冷启动",
      "en": "Cold Start",
      "cat": "抖音",
      "def": "新账号 / 新直播间的初始流量阶段",
      "ex": "冷启动期需要熬过前 5 场。"
    },
    {
      "id": 97,
      "cn": "赛马机制",
      "en": "Horse Racing Mechanism",
      "cat": "抖音",
      "def": "多条视频 / 多场直播竞争，数据好的获得流量倾斜",
      "ex": "一次发 5 条视频，让赛马机制选出爆款。"
    },
    {
      "id": 98,
      "cn": "单品直播",
      "en": "Single Product Live",
      "cat": "抖音",
      "def": "整场只讲一个产品",
      "ex": "适合高客单价产品的直播模式。"
    },
    {
      "id": 99,
      "cn": "笔记",
      "en": "Note",
      "cat": "小红书",
      "def": "小红书的内容单元（图文 / 视频）",
      "ex": "这篇笔记爆了，收藏破万。"
    },
    {
      "id": 100,
      "cn": "薯条",
      "en": "Shutiao",
      "cat": "小红书",
      "def": "小红书官方内容加热工具",
      "ex": "投了 200 块薯条，笔记曝光涨了 5 万。"
    },
    {
      "id": 101,
      "cn": "蒲公英",
      "en": "Dandelion",
      "cat": "小红书",
      "def": "小红书官方达人合作平台",
      "ex": "品牌通过蒲公英下单有数据保障。"
    },
    {
      "id": 102,
      "cn": "爆文",
      "en": "Viral Note",
      "cat": "小红书",
      "def": "数据表现优异的笔记（通常点赞 > 1000）",
      "ex": "出爆文后粉丝涨了一万。"
    },
    {
      "id": 103,
      "cn": "收录",
      "en": "Indexing",
      "cat": "小红书",
      "def": "笔记被系统索引，可通过搜索找到",
      "ex": "笔记没收录，搜索标题都找不到。"
    },
    {
      "id": 104,
      "cn": "关键词优化",
      "en": "Keyword Optimization",
      "cat": "小红书",
      "def": "在标题 / 正文 / 标签中布局搜索词",
      "ex": "关键词优化做好搜索流量翻倍。"
    },
    {
      "id": 105,
      "cn": "SEO",
      "en": "Search Engine Optimization",
      "cat": "小红书",
      "def": "搜索排名优化，让笔记在搜索结果靠前",
      "ex": "小红书 SEO 核心是标题和标签。"
    },
    {
      "id": 106,
      "cn": "搜索流量",
      "en": "Search Traffic",
      "cat": "小红书",
      "def": "用户通过搜索找到的流量",
      "ex": "搜索流量更精准，转化率高。"
    },
    {
      "id": 107,
      "cn": "长尾流量",
      "en": "Long-Tail Traffic",
      "cat": "小红书",
      "def": "低竞争关键词带来的持续流量",
      "ex": "长尾流量积累起来很可观。"
    },
    {
      "id": 108,
      "cn": "KFS",
      "en": "KOL+Fans+Search",
      "cat": "小红书",
      "def": "KOL+ 素人 + 搜索的组合打法",
      "ex": "KFS 打法是小红书标准投放模型。"
    },
    {
      "id": 109,
      "cn": "商业笔记",
      "en": "Sponsored Note",
      "cat": "小红书",
      "def": "标注赞助或广告的商业内容",
      "ex": "商业笔记需要走蒲公英报备。"
    },
    {
      "id": 110,
      "cn": "报备笔记",
      "en": "Reported Note",
      "cat": "小红书",
      "def": "通过蒲公英平台下单的合规商业内容",
      "ex": "不报备的商业笔记容易被判违规。"
    },
    {
      "id": 111,
      "cn": "软广",
      "en": "Soft Ad",
      "cat": "小红书",
      "def": "隐性广告，不明显标注商业属性",
      "ex": "软广要写得像真实分享。"
    },
    {
      "id": 112,
      "cn": "硬广",
      "en": "Hard Ad",
      "cat": "小红书",
      "def": "明显的广告宣传",
      "ex": "硬广转化率低但品牌曝光好。"
    },
    {
      "id": 113,
      "cn": "合集",
      "en": "Collection",
      "cat": "小红书",
      "def": "将多篇笔记归类整理",
      "ex": "把产品测评做成合集方便查找。"
    },
    {
      "id": 114,
      "cn": "置顶",
      "en": "Pinned",
      "cat": "小红书",
      "def": "将重要笔记固定在主页顶部",
      "ex": "置顶三篇分别是品牌 / 爆款 / 福利。"
    },
    {
      "id": 115,
      "cn": "评论区运营",
      "en": "Comment Management",
      "cat": "小红书",
      "def": "通过回复评论引导互动 / 转化",
      "ex": "评论区运营能提升 30% 转化。"
    },
    {
      "id": 116,
      "cn": "私信转化",
      "en": "DM Conversion",
      "cat": "小红书",
      "def": "通过私信完成咨询 / 销售",
      "ex": "高客单价产品适合私信转化。"
    },
    {
      "id": 117,
      "cn": "群聊",
      "en": "Group Chat",
      "cat": "小红书",
      "def": "小红书粉丝群功能",
      "ex": "群聊是私域沉淀的新方式。"
    },
    {
      "id": 118,
      "cn": "号店一体",
      "en": "Account-Store Integration",
      "cat": "小红书",
      "def": "账号与店铺打通，直接购买",
      "ex": "号店一体缩短购买路径。"
    },
    {
      "id": 119,
      "cn": "专业号",
      "en": "Pro Account",
      "cat": "小红书",
      "def": "企业 / 机构认证账号",
      "ex": "专业号可以挂店铺和联系方式。"
    },
    {
      "id": 120,
      "cn": "个人号",
      "en": "Personal Account",
      "cat": "小红书",
      "def": "个人用户账号",
      "ex": "个人号更适合做真实分享。"
    },
    {
      "id": 121,
      "cn": "跨界",
      "en": "Crossover",
      "cat": "小红书",
      "def": "不同领域的内容 / 品牌合作",
      "ex": "这次跨界合作双方粉丝都涨了。"
    },
    {
      "id": 122,
      "cn": "旗舰机",
      "en": "Flagship",
      "cat": "3C 数码",
      "def": "品牌最高端、配置最强的产品",
      "ex": "这款旗舰机搭载最新骁龙处理器。"
    },
    {
      "id": 123,
      "cn": "次旗舰",
      "en": "Sub-Flagship",
      "cat": "3C 数码",
      "def": "配置接近旗舰但价格更低的产品",
      "ex": "次旗舰性价比更高，核心功能都有。"
    },
    {
      "id": 124,
      "cn": "中端机",
      "en": "Mid-Range",
      "cat": "3C 数码",
      "def": "定位中等价位、配置均衡的产品",
      "ex": "中端机走量，是销量主力。"
    },
    {
      "id": 125,
      "cn": "入门机",
      "en": "Entry-Level",
      "cat": "3C 数码",
      "def": "低价位、基础配置的产品",
      "ex": "入门机适合预算有限的用户。"
    },
    {
      "id": 126,
      "cn": "性价比",
      "en": "Cost Performance",
      "cat": "3C 数码",
      "def": "性能与价格的比例",
      "ex": "这款手机性价比超高。"
    },
    {
      "id": 127,
      "cn": "水桶机",
      "en": "All-Rounder",
      "cat": "3C 数码",
      "def": "各方面配置均衡、无明显短板的产品",
      "ex": "水桶机没有亮点但也不会踩坑。"
    },
    {
      "id": 128,
      "cn": "偏科机",
      "en": "Specialized",
      "cat": "3C 数码",
      "def": "某些方面很强但其他方面有短板的产品",
      "ex": "游戏手机是典型的偏科机。"
    },
    {
      "id": 129,
      "cn": "骁龙",
      "en": "Snapdragon",
      "cat": "3C 数码",
      "def": "高通公司移动处理器系列",
      "ex": "骁龙 8 Gen3 是安卓旗舰标配。"
    },
    {
      "id": 130,
      "cn": "天玑",
      "en": "Dimensity",
      "cat": "3C 数码",
      "def": "联发科移动处理器系列",
      "ex": "天玑 9300 性能追平骁龙。"
    },
    {
      "id": 131,
      "cn": "高刷屏",
      "en": "High Refresh Rate",
      "cat": "3C 数码",
      "def": "高刷新率屏幕（90Hz/120Hz/144Hz）",
      "ex": "120Hz 高刷屏滑动更流畅。"
    },
    {
      "id": 132,
      "cn": "快充",
      "en": "Fast Charging",
      "cat": "3C 数码",
      "def": "快速充电技术",
      "ex": "120W 快充 20 分钟充满。"
    },
    {
      "id": 133,
      "cn": "无线充",
      "en": "Wireless Charging",
      "cat": "3C 数码",
      "def": "无线充电功能",
      "ex": "支持 50W 无线快充。"
    },
    {
      "id": 134,
      "cn": "IP68",
      "en": "IP68 Rating",
      "cat": "3C 数码",
      "def": "防尘防水等级",
      "ex": "IP68 防水可以水下拍照。"
    },
    {
      "id": 135,
      "cn": "NFC",
      "en": "NFC",
      "cat": "3C 数码",
      "def": "近场通信功能",
      "ex": "NFC 可以刷公交和门禁。"
    },
    {
      "id": 136,
      "cn": "红外",
      "en": "Infrared",
      "cat": "3C 数码",
      "def": "红外遥控功能",
      "ex": "红外可以当遥控器用。"
    },
    {
      "id": 137,
      "cn": "3.5mm 耳机孔",
      "en": "3.5mm Jack",
      "cat": "3C 数码",
      "def": "传统耳机接口",
      "ex": "保留 3.5mm 耳机孔好评。"
    },
    {
      "id": 138,
      "cn": "Type-C",
      "en": "Type-C",
      "cat": "3C 数码",
      "def": "通用 USB 接口",
      "ex": "全系标配 Type-C 接口。"
    },
    {
      "id": 139,
      "cn": "LTPO",
      "en": "LTPO",
      "cat": "3C 数码",
      "def": "自适应刷新率屏幕技术",
      "ex": "LTPO 屏幕更省电。"
    },
    {
      "id": 140,
      "cn": "OLED",
      "en": "OLED",
      "cat": "3C 数码",
      "def": "有机发光二极管屏幕",
      "ex": "OLED 屏幕色彩更鲜艳。"
    },
    {
      "id": 141,
      "cn": "LCD",
      "en": "LCD",
      "cat": "3C 数码",
      "def": "液晶显示屏",
      "ex": "LCD 屏幕更护眼。"
    },
    {
      "id": 142,
      "cn": "跑分",
      "en": "Benchmark Score",
      "cat": "3C 数码",
      "def": "性能测试软件得分（安兔兔等）",
      "ex": "安兔兔跑分破 200 万。"
    },
    {
      "id": 143,
      "cn": "果粉",
      "en": "Apple Fan",
      "cat": "3C 数码",
      "def": "苹果品牌忠实粉丝",
      "ex": "果粉会无条件支持新品。"
    },
    {
      "id": 144,
      "cn": "米粉",
      "en": "Mi Fan",
      "cat": "3C 数码",
      "def": "小米品牌忠实粉丝",
      "ex": "米粉节销量破纪录。"
    },
    {
      "id": 145,
      "cn": "花粉",
      "en": "Huawei Fan",
      "cat": "3C 数码",
      "def": "华为品牌忠实粉丝",
      "ex": "花粉对华为忠诚度很高。"
    },
    {
      "id": 146,
      "cn": "索粉",
      "en": "Sony Fan",
      "cat": "3C 数码",
      "def": "索尼品牌忠实粉丝",
      "ex": "索粉信仰充值。"
    },
    {
      "id": 147,
      "cn": "参数党",
      "en": "Spec Enthusiast",
      "cat": "3C 数码",
      "def": "注重硬件参数的用户",
      "ex": "参数党只看跑分和配置。"
    },
    {
      "id": 148,
      "cn": "性能党",
      "en": "Performance User",
      "cat": "3C 数码",
      "def": "注重性能表现的用户",
      "ex": "性能党首选游戏手机。"
    },
    {
      "id": 149,
      "cn": "颜值党",
      "en": "Design User",
      "cat": "3C 数码",
      "def": "注重外观设计的用户",
      "ex": "颜值党为设计买单。"
    },
    {
      "id": 150,
      "cn": "实用党",
      "en": "Practical User",
      "cat": "3C 数码",
      "def": "注重实用性的用户",
      "ex": "实用党不追求旗舰配置。"
    },
    {
      "id": 151,
      "cn": "首发党",
      "en": "Early Adopter",
      "cat": "3C 数码",
      "def": "喜欢第一时间购买新品的用户",
      "ex": "首发党不怕踩坑。"
    },
    {
      "id": 152,
      "cn": "等等党",
      "en": "Wait-And-See",
      "cat": "3C 数码",
      "def": "等待降价或下一代产品的用户",
      "ex": "等等党永远不亏。"
    },
    {
      "id": 153,
      "cn": "保值党",
      "en": "Resale Value User",
      "cat": "3C 数码",
      "def": "关注产品保值率的用户",
      "ex": "保值党首选苹果。"
    },
    {
      "id": 154,
      "cn": "首发",
      "en": "Launch",
      "cat": "3C 数码",
      "def": "新产品首次公开发售",
      "ex": "首发当天销量破 10 万台。"
    },
    {
      "id": 155,
      "cn": "预售",
      "en": "Pre-Order",
      "cat": "3C 数码",
      "def": "正式发售前的预订",
      "ex": "预售定金 100 抵 300。"
    },
    {
      "id": 156,
      "cn": "抢购",
      "en": "Flash Sale",
      "cat": "3C 数码",
      "def": "限量限时购买",
      "ex": "整点抢购，一秒售罄。"
    },
    {
      "id": 157,
      "cn": "现货",
      "en": "In Stock",
      "cat": "3C 数码",
      "def": "可立即购买发货",
      "ex": "不用等，现在有现货。"
    },
    {
      "id": 158,
      "cn": "期货",
      "en": "Backorder",
      "cat": "3C 数码",
      "def": "需要等待一段时间发货",
      "ex": "这款是期货，要等一个月。"
    },
    {
      "id": 159,
      "cn": "黄牛",
      "en": "Scalper",
      "cat": "3C 数码",
      "def": "倒卖产品赚差价的中间商",
      "ex": "黄牛加价 500 倒卖。"
    },
    {
      "id": 160,
      "cn": "官网",
      "en": "Official Website",
      "cat": "3C 数码",
      "def": "品牌官方销售渠道",
      "ex": "官网购买最靠谱。"
    },
    {
      "id": 161,
      "cn": "旗舰店",
      "en": "Flagship Store",
      "cat": "3C 数码",
      "def": "品牌官方授权的线上 / 线下店铺",
      "ex": "天猫旗舰店是官方渠道。"
    },
    {
      "id": 162,
      "cn": "授权店",
      "en": "Authorized Store",
      "cat": "3C 数码",
      "def": "品牌授权的销售店铺",
      "ex": "授权店有官方保修。"
    },
    {
      "id": 163,
      "cn": "水货",
      "en": "Gray Market",
      "cat": "3C 数码",
      "def": "非正规渠道进口的产品",
      "ex": "水货便宜但没有保修。"
    },
    {
      "id": 164,
      "cn": "行货",
      "en": "Official Import",
      "cat": "3C 数码",
      "def": "正规渠道销售的产品",
      "ex": "行货有官方保修更放心。"
    },
    {
      "id": 165,
      "cn": "港版",
      "en": "HK Version",
      "cat": "3C 数码",
      "def": "香港版本的产品",
      "ex": "港版比国行便宜一千。"
    },
    {
      "id": 166,
      "cn": "美版",
      "en": "US Version",
      "cat": "3C 数码",
      "def": "美国版本的产品",
      "ex": "美版 iPhone 没有实体 SIM 卡槽。"
    },
    {
      "id": 167,
      "cn": "激活",
      "en": "Activation",
      "cat": "3C 数码",
      "def": "首次使用产品并注册",
      "ex": "激活后不支持七天无理由。"
    },
    {
      "id": 168,
      "cn": "未激活",
      "en": "Unactivated",
      "cat": "3C 数码",
      "def": "全新未使用状态",
      "ex": "未激活的机器价格更高。"
    },
    {
      "id": 169,
      "cn": "首发价",
      "en": "Launch Price",
      "cat": "3C 数码",
      "def": "新产品首次发售的价格",
      "ex": "首发价 3999 元起。"
    },
    {
      "id": 170,
      "cn": "破发",
      "en": "Price Break",
      "cat": "3C 数码",
      "def": "价格跌破首发价",
      "ex": "发布一个月就破发了。"
    },
    {
      "id": 171,
      "cn": "跳水",
      "en": "Price Drop",
      "cat": "3C 数码",
      "def": "价格大幅下跌",
      "ex": "这款手机价格跳水太快。"
    },
    {
      "id": 172,
      "cn": "保值率",
      "en": "Resale Value",
      "cat": "3C 数码",
      "def": "二手价格与原价的比例",
      "ex": "苹果保值率最高。"
    },
    {
      "id": 173,
      "cn": "以旧换新",
      "en": "Trade-In",
      "cat": "3C 数码",
      "def": "用旧设备抵扣购买新设备",
      "ex": "以旧换新最高抵 2000。"
    },
    {
      "id": 174,
      "cn": "分期免息",
      "en": "Interest-Free Installment",
      "cat": "3C 数码",
      "def": "分期付款无利息",
      "ex": "24 期分期免息很划算。"
    },
    {
      "id": 175,
      "cn": "学生价",
      "en": "Student Discount",
      "cat": "3C 数码",
      "def": "面向学生的优惠价格",
      "ex": "学生价优惠 200 元。"
    },
    {
      "id": 176,
      "cn": "以租代购",
      "en": "Rent-To-Own",
      "cat": "3C 数码",
      "def": "租赁方式最终获得产品",
      "ex": "以租代购降低购机门槛。"
    },
    {
      "id": 177,
      "cn": "评测",
      "en": "Review",
      "cat": "3C 数码",
      "def": "专业或用户的产品测试评价",
      "ex": "等评测出来再决定买不买。"
    },
    {
      "id": 178,
      "cn": "开箱",
      "en": "Unboxing",
      "cat": "3C 数码",
      "def": "首次打开产品包装并展示",
      "ex": "开箱视频播放量 100 万。"
    },
    {
      "id": 179,
      "cn": "上手",
      "en": "Hands-On",
      "cat": "3C 数码",
      "def": "实际使用体验",
      "ex": "上手感觉手感不错。"
    },
    {
      "id": 180,
      "cn": "深度体验",
      "en": "In-Depth Review",
      "cat": "3C 数码",
      "def": "长期使用后的详细评价",
      "ex": "深度体验一周后的感受。"
    },
    {
      "id": 181,
      "cn": "智商税",
      "en": "IQ Tax",
      "cat": "3C 数码",
      "def": "不值得购买的产品",
      "ex": "这款手环是智商税。"
    },
    {
      "id": 182,
      "cn": "信仰充值",
      "en": "Faith Recharge",
      "cat": "3C 数码",
      "def": "为品牌情怀买单",
      "ex": "索尼大法好，信仰充值。"
    },
    {
      "id": 183,
      "cn": "挤牙膏",
      "en": "Toothpaste Squeezing",
      "cat": "3C 数码",
      "def": "产品升级幅度很小",
      "ex": "这一代又是挤牙膏。"
    },
    {
      "id": 184,
      "cn": "刀法精准",
      "en": "Precise Cutting",
      "cat": "3C 数码",
      "def": "产品定位和配置划分精确",
      "ex": "老黄刀法精准，每个价位都有。"
    },
    {
      "id": 185,
      "cn": "保修",
      "en": "Warranty",
      "cat": "3C 数码",
      "def": "免费维修服务",
      "ex": "全国联保一年。"
    },
    {
      "id": 186,
      "cn": "延保",
      "en": "Extended Warranty",
      "cat": "3C 数码",
      "def": "延长保修期服务",
      "ex": "买延保多保一年。"
    },
    {
      "id": 187,
      "cn": "七天无理由",
      "en": "7-Day Return",
      "cat": "3C 数码",
      "def": "七天内可无理由退货",
      "ex": "激活后不支持七天无理由。"
    },
    {
      "id": 188,
      "cn": "三包",
      "en": "Three Guarantees",
      "cat": "3C 数码",
      "def": "包修、包换、包退",
      "ex": "三包政策保护消费者。"
    },
    {
      "id": 189,
      "cn": "官方售后",
      "en": "Official Service",
      "cat": "3C 数码",
      "def": "品牌官方维修服务",
      "ex": "官方售后价格贵但靠谱。"
    },
    {
      "id": 190,
      "cn": "第三方维修",
      "en": "Third-Party Repair",
      "cat": "3C 数码",
      "def": "非官方维修服务",
      "ex": "第三方维修便宜但可能用副厂件。"
    },
    {
      "id": 191,
      "cn": "换屏",
      "en": "Screen Replacement",
      "cat": "3C 数码",
      "def": "更换屏幕维修",
      "ex": "换屏要 2000 块太贵了。"
    },
    {
      "id": 192,
      "cn": "换电池",
      "en": "Battery Replacement",
      "cat": "3C 数码",
      "def": "更换电池服务",
      "ex": "用两年可以换电池。"
    },
    {
      "id": 193,
      "cn": "二手",
      "en": "Used",
      "cat": "3C 数码",
      "def": "已使用过的产品",
      "ex": "二手价格更划算。"
    },
    {
      "id": 194,
      "cn": "伊拉克成色",
      "en": "Poor Condition",
      "cat": "3C 数码",
      "def": "成色很差、磨损严重的二手",
      "ex": "伊拉克成色价格很低。"
    },
    {
      "id": 195,
      "cn": "单机",
      "en": "Device Only",
      "cat": "3C 数码",
      "def": "只有主机无配件",
      "ex": "单机便宜但没配件。"
    },
    {
      "id": 196,
      "cn": "在保",
      "en": "Under Warranty",
      "cat": "3C 数码",
      "def": "仍在保修期内",
      "ex": "在保机器更值钱。"
    },
    {
      "id": 197,
      "cn": "过保",
      "en": "Out Of Warranty",
      "cat": "3C 数码",
      "def": "已过保修期",
      "ex": "过保机器价格低。"
    },
    {
      "id": 198,
      "cn": "面交",
      "en": "In-Person Deal",
      "cat": "3C 数码",
      "def": "当面交易",
      "ex": "面交可以验货更放心。"
    },
    {
      "id": 199,
      "cn": "屠龙刀",
      "en": "Lowball Offer",
      "cat": "3C 数码",
      "def": "砍价幅度很大的买家",
      "ex": "遇到屠龙刀直接拉黑。"
    },
    {
      "id": 200,
      "cn": "头部达人",
      "en": "Mega Creator",
      "cat": "Social",
      "def": "",
      "ex": "头部达人一条视频报价 50 万。"
    },
    {
      "id": 201,
      "cn": "腰部达人",
      "en": "Macro Creator",
      "cat": "Social",
      "def": "",
      "ex": "腰部达人性价比最高。"
    },
    {
      "id": 202,
      "cn": "尾部达人",
      "en": "Micro Creator",
      "cat": "Social",
      "def": "",
      "ex": "尾部达人粉丝粘性更好。"
    },
    {
      "id": 203,
      "cn": "垂类达人",
      "en": "Niche Creator",
      "cat": "Social",
      "def": "专注某一细分领域的达人",
      "ex": "垂类达人转化更精准。"
    },
    {
      "id": 204,
      "cn": "跨界达人",
      "en": "Crossover Creator",
      "cat": "Social",
      "def": "跨领域合作的达人",
      "ex": "这次跨界达人合作效果意外好。"
    },
    {
      "id": 205,
      "cn": "虚拟达人",
      "en": "Virtual Creator",
      "cat": "Social",
      "def": "AI 生成的虚拟网红",
      "ex": "虚拟达人不会塌房。"
    },
    {
      "id": 206,
      "cn": "明星达人",
      "en": "Icon",
      "cat": "Social",
      "def": "有明星身份的达人",
      "ex": "明星达人自带流量。"
    },
    {
      "id": 207,
      "cn": "MCN",
      "en": "Multi-Channel Network",
      "cat": "Social",
      "def": "网红经纪公司，管理多个达人",
      "ex": "这家 MCN 旗下有 50 个达人。"
    },
    {
      "id": 208,
      "cn": "公会",
      "en": "Guild",
      "cat": "Social",
      "def": "直播平台的主播管理机构",
      "ex": "加入公会才有流量扶持。"
    },
    {
      "id": 209,
      "cn": "签约达人",
      "en": "Signed Creator",
      "cat": "Social",
      "def": "与 MCN 签独家合约的达人",
      "ex": "签约达人不能接私活。"
    },
    {
      "id": 210,
      "cn": "独立达人",
      "en": "Independent Creator",
      "cat": "Social",
      "def": "未签约的自由行达人",
      "ex": "独立达人报价更灵活。"
    },
    {
      "id": 211,
      "cn": "达人孵化",
      "en": "Creator Incubation",
      "cat": "Social",
      "def": "从零培养新人的过程",
      "ex": "达人孵化周期至少 3 个月。"
    },
    {
      "id": 212,
      "cn": "达人经纪",
      "en": "Creator Agency",
      "cat": "Social",
      "def": "代理达人商务合作的机构",
      "ex": "达人经纪抽成 30%。"
    },
    {
      "id": 213,
      "cn": "商单",
      "en": "Sponsored Content",
      "cat": "Social",
      "def": "商业合作内容",
      "ex": "这个月接了 5 个商单。"
    },
    {
      "id": 214,
      "cn": "置换",
      "en": "Product Exchange",
      "cat": "Social",
      "def": "用产品置换内容，无现金交易",
      "ex": "小达人接受纯置换。"
    },
    {
      "id": 215,
      "cn": "一口价",
      "en": "Flat Fee",
      "cat": "Social",
      "def": "固定费用合作",
      "ex": "头部达人只接一口价。"
    },
    {
      "id": 216,
      "cn": "底薪 + 提成",
      "en": "Base + Commission",
      "cat": "Social",
      "def": "保底费用加销售分成",
      "ex": "腰部达人接受底薪 + 提成。"
    },
    {
      "id": 217,
      "cn": "年框",
      "en": "Annual Framework",
      "cat": "Social",
      "def": "年度框架合作协议",
      "ex": "签年框价格更优惠。"
    },
    {
      "id": 218,
      "cn": "独家合作",
      "en": "Exclusive Partnership",
      "cat": "Social",
      "def": "排他性合作",
      "ex": "独家合作期间不能接竞品。"
    },
    {
      "id": 219,
      "cn": "联名款",
      "en": "Co-Branded Product",
      "cat": "Social",
      "def": "达人与品牌联合开发产品",
      "ex": "联名款首发销量破纪录。"
    },
    {
      "id": 220,
      "cn": "代言",
      "en": "Endorsement",
      "cat": "Social",
      "def": "担任品牌代言人",
      "ex": "签约代言一年 500 万。"
    },
    {
      "id": 221,
      "cn": "品牌大使",
      "en": "Brand Ambassador",
      "cat": "Social",
      "def": "品牌推广代表",
      "ex": "品牌大使比代言级别低。"
    },
    {
      "id": 222,
      "cn": "种草合作",
      "en": "Seeding Campaign",
      "cat": "Social",
      "def": "产品推荐合作",
      "ex": "种草合作要求真实体验。"
    },
    {
      "id": 223,
      "cn": "直播带货",
      "en": "Live Streaming Sales",
      "cat": "Social",
      "def": "直播中销售产品",
      "ex": "直播带货转化率最高。"
    },
    {
      "id": 224,
      "cn": "短视频带货",
      "en": "Short Video Commerce",
      "cat": "Social",
      "def": "短视频挂链接销售",
      "ex": "短视频带货适合长尾。"
    },
    {
      "id": 225,
      "cn": "粉丝量",
      "en": "Follower Count",
      "cat": "Social",
      "def": "账号粉丝总数",
      "ex": "粉丝量不等于购买力。"
    },
    {
      "id": 226,
      "cn": "活跃粉丝",
      "en": "Active Followers",
      "cat": "Social",
      "def": "实际互动的粉丝",
      "ex": "活跃粉丝占比更重要。"
    },
    {
      "id": 227,
      "cn": "僵尸粉",
      "en": "Fake Followers",
      "cat": "Social",
      "def": "虚假 / 不活跃粉丝",
      "ex": "刷僵尸粉会被平台处罚。"
    },
    {
      "id": 228,
      "cn": "互动率",
      "en": "Engagement Rate",
      "cat": "Social",
      "def": "点赞评论分享与粉丝比",
      "ex": "互动率 5% 算优秀。"
    },
    {
      "id": 229,
      "cn": "完播率",
      "en": "Completion Rate",
      "cat": "Social",
      "def": "视频完整观看比例",
      "ex": "完播率影响流量推荐。"
    },
    {
      "id": 230,
      "cn": "商单报价",
      "en": "Sponsorship Rate",
      "cat": "Social",
      "def": "商业合作报价",
      "ex": "商单报价参考粉丝量。"
    },
    {
      "id": 231,
      "cn": "CPM",
      "en": "Cost Per Mille",
      "cat": "Social",
      "def": "千次曝光成本",
      "ex": "CPM 控制在 50 以内。"
    },
    {
      "id": 232,
      "cn": "CPC",
      "en": "Cost Per Click",
      "cat": "Social",
      "def": "单次点击成本",
      "ex": "CPC 比信息流广告低。"
    },
    {
      "id": 233,
      "cn": "CPS",
      "en": "Cost Per Sale",
      "cat": "Social",
      "def": "按销售付费",
      "ex": "CPS 模式风险最低。"
    },
    {
      "id": 234,
      "cn": "种草视频",
      "en": "Seeding Video",
      "cat": "Social",
      "def": "产品推荐视频",
      "ex": "种草视频要真实自然。"
    },
    {
      "id": 235,
      "cn": "测评视频",
      "en": "Review Video",
      "cat": "Social",
      "def": "产品测试评价视频",
      "ex": "测评视频最影响购买决策。"
    },
    {
      "id": 236,
      "cn": "开箱视频",
      "en": "Unboxing Video",
      "cat": "Social",
      "def": "首次打开产品包装视频",
      "ex": "开箱视频播放量很高。"
    },
    {
      "id": 237,
      "cn": "Vlog",
      "en": "Vlog",
      "cat": "Social",
      "def": "日常生活记录视频",
      "ex": "Vlog 植入更自然。"
    },
    {
      "id": 238,
      "cn": "教程视频",
      "en": "Tutorial Video",
      "cat": "Social",
      "def": "使用教学视频",
      "ex": "教程视频收藏率高。"
    },
    {
      "id": 239,
      "cn": "挑战视频",
      "en": "Challenge Video",
      "cat": "Social",
      "def": "参与热门挑战的视频",
      "ex": "挑战视频容易爆。"
    },
    {
      "id": 240,
      "cn": "剧情视频",
      "en": "Story Video",
      "cat": "Social",
      "def": "有故事情节的视频",
      "ex": "剧情视频植入要巧妙。"
    },
    {
      "id": 241,
      "cn": "口播视频",
      "en": "Talking Head Video",
      "cat": "Social",
      "def": "对着镜头讲解的视频",
      "ex": "口播视频信任感强。"
    },
    {
      "id": 242,
      "cn": "植入",
      "en": "Product Placement",
      "cat": "Social",
      "def": "内容中嵌入产品",
      "ex": "软植入比硬广效果好。"
    },
    {
      "id": 243,
      "cn": "口播",
      "en": "Verbal Promotion",
      "cat": "Social",
      "def": "口头推荐产品",
      "ex": "口播要自然不生硬。"
    },
    {
      "id": 244,
      "cn": "挂车",
      "en": "Link In Cart",
      "cat": "Social",
      "def": "视频 / 直播挂购买链接",
      "ex": "挂车转化路径最短。"
    },
    {
      "id": 245,
      "cn": "恰饭",
      "en": "Monetization",
      "cat": "Social",
      "def": "接商业内容赚钱",
      "ex": "博主也要恰饭嘛。"
    },
    {
      "id": 246,
      "cn": "割韭菜",
      "en": "Cash Grab",
      "cat": "Social",
      "def": "利用粉丝信任变现",
      "ex": "割韭菜走不长远。"
    },
    {
      "id": 247,
      "cn": "立人设",
      "en": "Build Persona",
      "cat": "Social",
      "def": "塑造人物形象",
      "ex": "人设不能崩。"
    },
    {
      "id": 248,
      "cn": "蹭热度",
      "en": "Ride The Hype",
      "cat": "Social",
      "def": "借势热门话题",
      "ex": "蹭热度要快。"
    },
    {
      "id": 249,
      "cn": "控评",
      "en": "Comment Control",
      "cat": "Social",
      "def": "管理评论区内容",
      "ex": "负面太多需要控评。"
    },
    {
      "id": 250,
      "cn": "数据造假",
      "en": "Data Fraud",
      "cat": "Social",
      "def": "刷量刷粉等行为",
      "ex": "数据造假会被平台封禁。"
    },
    {
      "id": 251,
      "cn": "代理式 AI",
      "en": "Agentic AI",
      "cat": "NEW",
      "def": "能够自主执行任务的 AI 系统，消费者用它来研究、推荐和购买产品",
      "ex": "Brands must adapt as consumers increasingly rely on agentic AI."
    },
    {
      "id": 252,
      "cn": "快速广告",
      "en": "Fastvertising",
      "cat": "NEW",
      "def": "快速响应热点事件并病毒式传播的广告形式",
      "ex": "Their fastvertising campaign capitalized on the viral moment."
    },
    {
      "id": 253,
      "cn": "合成用户画像",
      "en": "Synthetic Personas",
      "cat": "NEW",
      "def": "用 AI 生成的虚拟消费者形象，用于市场研究",
      "ex": "Synthetic personas accelerate market research cycles."
    },
    {
      "id": 254,
      "cn": "数字孪生",
      "en": "Digital Twins",
      "cat": "NEW",
      "def": "消费者行为的数字化模拟，用于预测购买决策",
      "ex": "Digital twins help test marketing scenarios risk-free."
    },
    {
      "id": 255,
      "cn": "AI劣质内容",
      "en": "AL Slop",
      "cat": "NEW",
      "def": "那些重复、低质、缺乏人工筛选与价值加持的内容",
      "ex": ""
    },
    {
      "id": 256,
      "cn": "多模态化",
      "en": "Multi-modality",
      "cat": "NEW",
      "def": "社交媒体不再仅仅是“内容分发渠道”而是多种不同形式或感知渠道",
      "ex": "Treat social as a discovery engine, not just a disctribution channel."
    },
    {
      "id": 257,
      "cn": "必备条件",
      "en": "Table Stakes",
      "cat": "NEW",
      "def": "原指参与游戏必须支付的最低筹码，商业中表示必备条件/最低标准",
      "ex": "AI tools have simply become table stakes for brainstorming."
    },
    {
      "id": 1001,
      "cn": "KOS",
      "en": "Key Opinion Sales",
      "cat": "小红书",
      "def": "在销售场景中，具备专业影响力并能够通过内容、讲解或互动直接促成购买决策的人。",
      "ex": "小红书的 KOS 转化都还不错",
      "contributor": "zan",
      "addedAt": "2026-03-27"
    }
  ]
}